myicomfort/__init__.py
myicomfort/api.py
myicomfort-0.7.0.dist-info/LICENSE
myicomfort-0.7.0.dist-info/METADATA
myicomfort-0.7.0.dist-info/WHEEL
myicomfort-0.7.0.dist-info/top_level.txt
myicomfort-0.7.0.dist-info/RECORD
