Metadata-Version: 2.1
Name: myicomfort
Version: 0.7.0
Summary: API Wrapper for myicomfort.com
Home-page: https://github.com/thevoltagesource/myicomfort
Author: Jacob Southard
Author-email: jacob@thevoltagesource.com
Classifier: Programming Language :: Python :: 3
Classifier: License :: OSI Approved :: MIT License
Classifier: Operating System :: OS Independent
License-File: LICENSE
Requires-Dist: requests
